HISTORY.md
LICENSE
MANIFEST.in
README.md
setup.py
examples/mult_cmd.py
examples/provisioning.py
examples/read_write_record.py
pyonep/__init__.py
pyonep/datastore.py
pyonep/exceptions.py
pyonep/onep.py
pyonep/provision.py
pyonep.egg-info/PKG-INFO
pyonep.egg-info/SOURCES.txt
pyonep.egg-info/dependency_links.txt
pyonep.egg-info/not-zip-safe
pyonep.egg-info/top_level.txt