Metadata-Version: 1.0
Name: pyonep
Version: 0.7.1
Summary: Python bindings for Exosite API over HTTP JSON RPC.
Home-page: http://github.com/exosite-labs/pyonep
Author: Exosite
Author-email: labs@exosite.com
License: UNKNOWN
Keywords: exosite,onep,one platform,m2m
Platform: UNKNOWN
